brag/__init__.py
brag/chat.py
brag/db.py
brag/defaults.py
brag/emb.py
brag/index.py
brag/repl.py
brag/styles.py
brag/ui.py
brag/util.py
brag/rags/__init__.py
brag/rags/abstract.py
brag/rags/brag.py
brag/rags/trag.py
pybrag-0.0.30.dist-info/licenses/LICENSE.md
pybrag-0.0.30.dist-info/METADATA
pybrag-0.0.30.dist-info/WHEEL
pybrag-0.0.30.dist-info/entry_points.txt
pybrag-0.0.30.dist-info/top_level.txt
pybrag-0.0.30.dist-info/RECORD
