Metadata-Version: 2.4
Name: pybrag
Version: 0.0.30
Summary: Basic RAG
Author-email: Arthur Lui <alui@lanl.gov>
License-Expression: MIT
Project-URL: Homepage, https://github.com/lanl/brag
Project-URL: Documentation, https://lanl.github.io/brag
Project-URL: Repository, https://github.com/lanl/brag
Project-URL: Issues, https://github.com/lanl/brag/issues
Project-URL: Changelog, https://github.com/lanl/brag/blob/master/CHANGELOG.md
Classifier: Operating System :: OS Independent
Classifier: Programming Language :: Python :: 3.10
Classifier: Programming Language :: Python :: 3.11
Classifier: Programming Language :: Python :: 3.12
Classifier: Programming Language :: Python :: 3.13
Classifier: Programming Language :: Python :: 3.14
Requires-Python: >=3.12
License-File: LICENSE.md
Requires-Dist: gradio~=5.33.0
Requires-Dist: fastapi<0.116,>=0.115.7
Requires-Dist: langchain<0.4,>=0.3.27
Requires-Dist: langchain-chroma>=0.2.6
Requires-Dist: langchain-community<0.4,>=0.3.29
Requires-Dist: langchain-core>=0.3.31
Requires-Dist: langchain-litellm<0.3,>=0.2.3
Requires-Dist: langchain-ollama<0.4,>=0.3.10
Requires-Dist: langchain-openai>=0.3.35
Requires-Dist: langgraph<0.7,>=0.6.6
Requires-Dist: docx2txt>=0.9
Requires-Dist: pydantic<3.0,>=2.10.6
Requires-Dist: pymupdf4llm<0.1,>=0.0.17
Requires-Dist: pypdf<6.0,>=5.1.0
Requires-Dist: typer>=0.19
Requires-Dist: unstructured>=0.18.15
Dynamic: license-file
